Simon/Simon.srcs/sources_1/new/encoder.sv
`timescale 1ns / 1ps

module encoder_param #(
    parameter N = 4  
)(
    input  logic [N-1:0] encoder_in,
    input  logic         enable,
    output logic [$clog2(N)-1:0] binary_out //clog2 devuelve el número de bits necesarios para representar N valores distintos
);

    integer i;

    always_comb begin
        binary_out = 0;
        if (enable) begin
            for (i = 0; i < N; i++) begin
                if (encoder_in[i])
                    binary_out = i; //él mismo lo coniverte a binario
            end
        end
    end

endmodule


// N: número de entradas
// binary_out: número en binario que da la salida
// Revisa cada posición de N y verifica cuál es uno para sacar ese número en la salida.

Simon/Simon.srcs/sources_1/new/encoder_tb.sv
`timescale 1ns / 1ps


module encoder_param_tb;

    // Parámetro
    parameter N = 4;

    // Señales
    logic [N-1:0] encoder_in;
    logic enable;
    logic [$clog2(N)-1:0] binary_out;

    // Instancia del DUT (Device Under Test)
    encoder_param #(.N(N)) dut (
        .encoder_in(encoder_in),
        .enable(enable),
        .binary_out(binary_out)
    );

    
    initial begin
        
        // Archivo para GTKWave (cambiar en Vivado (: )
        $dumpfile("encoder_param_tb.vcd");
        $dumpvars(0, encoder_param_tb);

        // Inicialización
        enable = 0;
        encoder_in = 0;

        #10;
        enable = 1;

        // Probar cada entrada individual
        #10 encoder_in = 4'b0001;  // Esperado: 0
        #10 encoder_in = 4'b0010;  // Esperado: 1
        #10 encoder_in = 4'b0100;  // Esperado: 2
        #10 encoder_in = 4'b1000;  // Esperado: 3

        // Caso con múltiples bits activos (prioridad al mayor índice)
        #10 encoder_in = 4'b1010;  // Resultado esperado: 3

        // Deshabilitar
        #10 enable = 0;
        #10 encoder_in = 4'b0100;

        #20;
        $finish;
    end

endmodule

Simon/Simon.sim/sim_1/behav/xsim/encoder_param_tb.vcd
$date
   Sun Mar  1 12:57:42 2026
$end

$version
  2025.2
  $dumpfile ("encoder_param_tb.vcd") 
$end

$timescale
  1ps
$end

$scope module encoder_param_tb $end
$var reg 4 ! encoder_in [3:0] $end
$var reg 1 " enable $end
$var reg 2 # binary_out [1:0] $end
$scope module dut $end
$var wire 4 $ encoder_in [3:0] $end
$var wire 1 % enable $end
$var reg 2 # binary_out [1:0] $end
$var integer 32 & i [31:0] $end
$upscope $end
$upscope $end
$enddefinitions $end

#0
$dumpvars
b0 !
0"
b0 #
b0 $
0%
bx &
$end

#10000
1"
1%
b100 &

#20000
b1 !
b1 $
b100 &

#30000
b10 !
b1 #
b10 $
b100 &

#40000
b100 !
b10 #
b100 $
b100 &

#50000
b1000 !
b11 #
b1000 $
b100 &

#60000
b1010 !
b11 #
b1010 $
b100 &

#70000
0"
b0 #
0%

#80000
b100 !
b100 $
