Simon/Simon.srcs/sources_1/new/decoder.sv
`timescale 1ns/1ps

module decoparam #(
    parameter N = 2
) (
    input logic [N-1:0] deco_in,
    
    output logic [(N**2)-1:0] deco_out
);

always_comb 
begin 
    deco_out = '0;
    deco_out[deco_in]=1'b1;
end
    
endmodule 

// N: número de entrada (binario)
// Out inicialmente es 0. Toma el in y lo convierte a decimal.
// Activa el bit en out que el index le indique, el index es el valor del in.
// Ejemplo si in es 110 (6), activa el bit 6 en la salida de derecha a izquierda.

EncoderDecoderVS/Decoder/decoparam_tb.sv
`timescale 1ns/1ps
`include "decoparam.sv"


module decoparam_tb;

    // Parámetro a probar
    parameter N = 3;

    // Señales
    logic [N-1:0] deco_in;
    logic [(N**2)-1:0] deco_out;

    // Instancia del DUT
    decoparam #(.N(N)) DUT (
        .deco_in(deco_in),
        .deco_out(deco_out)
    );

    // Generación de estímulos
    initial begin
        // Dump para GTKWave
        $dumpfile("decoparam_tb.vcd");
        $dumpvars(0, decoparam_tb);

        // Probar todos los valores posibles
        for (int i = 0; i < 2**N; i++) begin
            deco_in = i;
            #10;
        end

        #10;
        $finish;
    end

endmodule

EncoderDecoderVS/Decoder/decoparam_tb.vcd
$date
	Sat Feb 28 12:29:51 2026
$end
$version
	Icarus Verilog
$end
$timescale
	1ps
$end
$scope module decoparam_tb $end
$var wire 9 ! deco_out [8:0] $end
$var reg 3 " deco_in [2:0] $end
$scope module DUT $end
$var wire 3 # deco_in [2:0] $end
$var reg 9 $ deco_out [8:0] $end
$upscope $end
$scope begin $ivl_for_loop0 $end
$var integer 32 % i [31:0] $end
$upscope $end
$upscope $end
$enddefinitions $end
#0
$dumpvars
b0 %
b1 $
b0 #
b0 "
b1 !
$end
#10000
b10 !
b10 $
b1 "
b1 #
b1 %
#20000
b100 !
b100 $
b10 "
b10 #
b10 %
#30000
b1000 !
b1000 $
b11 "
b11 #
b11 %
#40000
b10000 !
b10000 $
b100 "
b100 #
b100 %
#50000
b100000 !
b100000 $
b101 "
b101 #
b101 %
#60000
b1000000 !
b1000000 $
b110 "
b110 #
b110 %
#70000
b10000000 !
b10000000 $
b111 "
b111 #
b111 %
#80000
b1000 %
